MANIFEST.in
README.markdown
ineedpy2.py
setup.py
ineedpy2.egg-info/PKG-INFO
ineedpy2.egg-info/SOURCES.txt
ineedpy2.egg-info/dependency_links.txt
ineedpy2.egg-info/top_level.txt