Metadata-Version: 1.0
Name: ineedpy2
Version: 1.01
Summary: Library to swap to newer python version on a multi-version system.
Home-page: https://github.com/linsomniac/ineedpy2
Author: Sean Reifschneider
Author-email: <jafo@tummy.com>
License: Python Software Foundation
Platform: UNKNOWN
